slimrpc/__init__.py
slimrpc/channel.py
slimrpc/common.py
slimrpc/context.py
slimrpc/py.typed
slimrpc/rpc.py
slimrpc/server.py
slimrpc/examples/simple/buf.gen.yaml
slimrpc/examples/simple/client.py
slimrpc/examples/simple/example.proto
slimrpc/examples/simple/server.py
slimrpc/examples/simple/types/example_pb2.py
slimrpc/examples/simple/types/example_pb2.pyi
slimrpc/examples/simple/types/example_pb2_slimrpc.py
slimrpc-0.1.0.dist-info/METADATA
slimrpc-0.1.0.dist-info/WHEEL
slimrpc-0.1.0.dist-info/entry_points.txt
slimrpc-0.1.0.dist-info/RECORD
